pyabi/__init__.py
pyabi_quadrable/__init__.py
tests/__init__.py
tests/test_pyabi.py
tests/test_pyabi_quadrable.py
PyABI_QUADRABLE-0.42.0.dist-info/LICENSE
PyABI_QUADRABLE-0.42.0.dist-info/LICENSE.md
PyABI_QUADRABLE-0.42.0.dist-info/METADATA
PyABI_QUADRABLE-0.42.0.dist-info/WHEEL
PyABI_QUADRABLE-0.42.0.dist-info/top_level.txt
PyABI_QUADRABLE-0.42.0.dist-info/RECORD
